terminal_llm_assistant/__init__.py
terminal_llm_assistant/cli.py
terminal_llm_assistant/server.py
terminal_llm_assistant/utils.py
terminal_llm_assistant/utils/__init__.py
terminal_llm_assistant-0.1.0.dist-info/licenses/LICENSE
tests/__init__.py
tests/test_basic.py
terminal_llm_assistant-0.1.0.dist-info/METADATA
terminal_llm_assistant-0.1.0.dist-info/WHEEL
terminal_llm_assistant-0.1.0.dist-info/entry_points.txt
terminal_llm_assistant-0.1.0.dist-info/top_level.txt
terminal_llm_assistant-0.1.0.dist-info/RECORD
