Metadata-Version: 2.4
Name: terminal-llm-assistant
Version: 0.1.0
Summary: Assistente de terminal que integra com a API do Google Gemini
Home-page: https://github.com/seuusuario/terminal-llm-assistant
Author: Angelo Vicente Filho
Author-email: Seu Nome <seu.email@empresa.com>
License: MIT
Project-URL: Homepage, https://github.com/seuusuario/terminal-llm-assistant
Project-URL: Bug Tracker, https://github.com/seuusuario/terminal-llm-assistant/issues
Classifier: Programming Language :: Python :: 3
Classifier: License :: OSI Approved :: MIT License
Classifier: Operating System :: OS Independent
Requires-Python: >=3.7
License-File: LICENSE
Requires-Dist: python-dotenv>=1.0.0
Requires-Dist: requests>=2.25.0
Requires-Dist: litellm>=1.0.0
Dynamic: author
Dynamic: home-page
Dynamic: license-file
Dynamic: requires-python
